kwnlp_dump_downloader/__init__.py
kwnlp_dump_downloader/argconfig.py
kwnlp_dump_downloader/cli_download_jobs.py
kwnlp_dump_downloader/cli_get_dump_status.py
kwnlp_dump_downloader/downloader.py
kwnlp_dump_downloader/dump_status.py
kwnlp_dump_downloader-0.1.0.dist-info/AUTHORS.md
kwnlp_dump_downloader-0.1.0.dist-info/LICENSE
kwnlp_dump_downloader-0.1.0.dist-info/METADATA
kwnlp_dump_downloader-0.1.0.dist-info/WHEEL
kwnlp_dump_downloader-0.1.0.dist-info/entry_points.txt
kwnlp_dump_downloader-0.1.0.dist-info/top_level.txt
kwnlp_dump_downloader-0.1.0.dist-info/RECORD
