Metadata-Version: 2.1
Name: kwnlp-dump-downloader
Version: 0.1.0
Summary: Utility for downloading and checking the status of Wikimedia dumps.
Home-page: https://github.com/kensho-technologies/kwnlp-dump-downloader
Author: Kensho Technologies LLC.
Author-email: kwnlp@kensho.com
License: Apache 2.0
Keywords: wikipedia download dump status open data
Platform: UNKNOWN
Classifier: Development Status :: 4 - Beta
Classifier: Intended Audience :: Developers
Classifier: License :: OSI Approved :: Apache Software License
Classifier: Programming Language :: Python :: 3 :: Only
Classifier: Programming Language :: Python :: 3
Classifier: Programming Language :: Python :: 3.6
Classifier: Programming Language :: Python :: 3.7
Classifier: Programming Language :: Python :: 3.8
Requires-Python: >=3.6
Requires-Dist: requests
Requires-Dist: wget
Requires-Dist: dataclasses (<1,>=0.7) ; python_version < "3.7"
Provides-Extra: dev
Requires-Dist: pre-commit ; extra == 'dev'
